{
  "timestamp": "2026-04-13 20:53:01",
  "data": {
    "KR": [
      {
        "trend": "호르 무즈",
        "search_volume": 5000000,
        "start_date": "~12",
        "analysis": "trending_up"
      },
      {
        "trend": "이상민",
        "search_volume": 5000000,
        "start_date": "~13",
        "analysis": "trending_up"
      },
      {
        "trend": "뉴스",
        "search_volume": 5000000,
        "start_date": "~22",
        "analysis": "trending_up"
      },
      {
        "trend": "잠수함",
        "search_volume": 2000000,
        "start_date": "~12",
        "analysis": "trending_up"
      },
      {
        "trend": "과즙세연",
        "search_volume": 2000000,
        "start_date": "~12",
        "analysis": "trending_up"
      },
      {
        "trend": "가스 폭발",
        "search_volume": 2000000,
        "start_date": "~17",
        "analysis": "trending_up"
      },
      {
        "trend": "롯데 자이언츠",
        "search_volume": 2000000,
        "start_date": "~15",
        "analysis": "trending_up"
      },
      {
        "trend": "바타",
        "search_volume": 2000000,
        "start_date": "~19",
        "analysis": "trending_up"
      },
      {
        "trend": "고유가 피해 지원금 신청",
        "search_volume": 2000000,
        "start_date": "~22",
        "analysis": "trending_up"
      },
      {
        "trend": "대한민국",
        "search_volume": 2000000,
        "start_date": "~14",
        "analysis": "timelapse"
      },
      {
        "trend": "맨유 대 리즈 유나이티드",
        "search_volume": 1000000,
        "start_date": "~2",
        "analysis": "trending_up"
      },
      {
        "trend": "베이비시터",
        "search_volume": 1000000,
        "start_date": "~10",
        "analysis": "trending_up"
      },
      {
        "trend": "김수미",
        "search_volume": 1000000,
        "start_date": "~16",
        "analysis": "trending_up"
      },
      {
        "trend": "김하성",
        "search_volume": 1000000,
        "start_date": "~12",
        "analysis": "trending_up"
      },
      {
        "trend": "허수아비",
        "search_volume": 1000000,
        "start_date": "~15",
        "analysis": "trending_up"
      },
      {
        "trend": "이성배",
        "search_volume": 1000000,
        "start_date": "~17",
        "analysis": "trending_up"
      },
      {
        "trend": "박용택",
        "search_volume": 1000000,
        "start_date": "~17",
        "analysis": "trending_up"
      },
      {
        "trend": "도라이버",
        "search_volume": 1000000,
        "start_date": "~18",
        "analysis": "trending_up"
      },
      {
        "trend": "신랑",
        "search_volume": 1000000,
        "start_date": "~22",
        "analysis": "trending_up"
      },
      {
        "trend": "김건희",
        "search_volume": 1000000,
        "start_date": "~11",
        "analysis": "trending_up"
      },
      {
        "trend": "선양소주",
        "search_volume": 1000000,
        "start_date": "~19",
        "analysis": "trending_up"
      },
      {
        "trend": "영화",
        "search_volume": 1000000,
        "start_date": "~17",
        "analysis": "trending_up"
      },
      {
        "trend": "파운드리",
        "search_volume": 1000000,
        "start_date": "~7",
        "analysis": "timelapse"
      },
      {
        "trend": "절벽",
        "search_volume": 5000,
        "start_date": "~14",
        "analysis": "trending_up"
      },
      {
        "trend": "광주광역시",
        "search_volume": 5000,
        "start_date": "~10",
        "analysis": "trending_up"
      }
    ],
    "US": [
      {
        "trend": "nba playoffs",
        "search_volume": 500000,
        "start_date": "~22",
        "analysis": "trending_up"
      },
      {
        "trend": "trump as jesus",
        "search_volume": 200000,
        "start_date": "~17",
        "analysis": "trending_up"
      },
      {
        "trend": "google",
        "search_volume": 200000,
        "start_date": "~8",
        "analysis": "timelapse"
      },
      {
        "trend": "man united vs leeds",
        "search_volume": 100000,
        "start_date": "~2",
        "analysis": "trending_up"
      },
      {
        "trend": "jazz vs lakers",
        "search_volume": 100000,
        "start_date": "~21",
        "analysis": "trending_up"
      },
      {
        "trend": "mcilroy green jacket presentation",
        "search_volume": 100000,
        "start_date": "~2",
        "analysis": "trending_up"
      },
      {
        "trend": "nuggets vs spurs",
        "search_volume": 100000,
        "start_date": "~15",
        "analysis": "timelapse"
      },
      {
        "trend": "magic vs celtics",
        "search_volume": 100000,
        "start_date": "~16",
        "analysis": "timelapse"
      },
      {
        "trend": "hbo max",
        "search_volume": 100000,
        "start_date": "~11",
        "analysis": "timelapse"
      },
      {
        "trend": "wordle hint",
        "search_volume": 100000,
        "start_date": "~1",
        "analysis": "timelapse"
      },
      {
        "trend": "ruby rose",
        "search_volume": 50000,
        "start_date": "~15",
        "analysis": "trending_up"
      },
      {
        "trend": "cancer",
        "search_volume": 50000,
        "start_date": "~21",
        "analysis": "trending_up"
      },
      {
        "trend": "scottie scheffler masters complaint",
        "search_volume": 50000,
        "start_date": "~8",
        "analysis": "trending_up"
      },
      {
        "trend": "warriors vs clippers",
        "search_volume": 50000,
        "start_date": "~20",
        "analysis": "timelapse"
      },
      {
        "trend": "cloud",
        "search_volume": 50000,
        "start_date": "~8",
        "analysis": "timelapse"
      },
      {
        "trend": "toluca - atl. san luis",
        "search_volume": 50000,
        "start_date": "~14",
        "analysis": "timelapse"
      },
      {
        "trend": "suns vs thunder",
        "search_volume": 50000,
        "start_date": "~15",
        "analysis": "timelapse"
      },
      {
        "trend": "hornets vs knicks",
        "search_volume": 50000,
        "start_date": "~16",
        "analysis": "timelapse"
      },
      {
        "trend": "cough drop recall",
        "search_volume": 202620000,
        "start_date": "~6",
        "analysis": "trending_up"
      },
      {
        "trend": "paxton lynch",
        "search_volume": 20000,
        "start_date": "~7",
        "analysis": "trending_up"
      },
      {
        "trend": "anna kepner",
        "search_volume": 20000,
        "start_date": "~4",
        "analysis": "trending_up"
      },
      {
        "trend": "bride",
        "search_volume": 20000,
        "start_date": "~9",
        "analysis": "trending_up"
      },
      {
        "trend": "trump family business expansion",
        "search_volume": 20000,
        "start_date": "~8",
        "analysis": "trending_up"
      },
      {
        "trend": "srh vs rr",
        "search_volume": 20000,
        "start_date": "~7",
        "analysis": "trending_up"
      }
    ],
    "JP": [
      {
        "trend": "京都 小学生 行方不明",
        "search_volume": 500000,
        "start_date": "~11",
        "analysis": "trending_up"
      },
      {
        "trend": "ヤフーニュース",
        "search_volume": 50000,
        "start_date": "~10",
        "analysis": "trending_up"
      },
      {
        "trend": "北原雅彦",
        "search_volume": 20000,
        "start_date": "~11",
        "analysis": "trending_up"
      },
      {
        "trend": "三浦祐太朗",
        "search_volume": 20000,
        "start_date": "~12",
        "analysis": "trending_up"
      },
      {
        "trend": "皇室典範",
        "search_volume": 20000,
        "start_date": "~22",
        "analysis": "trending_up"
      },
      {
        "trend": "園遊会",
        "search_volume": 20000,
        "start_date": "~15",
        "analysis": "trending_up"
      },
      {
        "trend": "mrs. green apple 風と町",
        "search_volume": 20000,
        "start_date": "~21",
        "analysis": "trending_up"
      },
      {
        "trend": "共犯者 洋平",
        "search_volume": 20000,
        "start_date": "~12",
        "analysis": "trending_up"
      },
      {
        "trend": "綾瀬はるか",
        "search_volume": 20000,
        "start_date": "~13",
        "analysis": "trending_up"
      },
      {
        "trend": "小田急",
        "search_volume": 20000,
        "start_date": "~18",
        "analysis": "trending_up"
      },
      {
        "trend": "かつや",
        "search_volume": 20000,
        "start_date": "~16",
        "analysis": "trending_up"
      },
      {
        "trend": "相席 食堂 不 適切",
        "search_volume": 20000,
        "start_date": "~9",
        "analysis": "trending_up"
      },
      {
        "trend": "観光客",
        "search_volume": 20000,
        "start_date": "~13",
        "analysis": "trending_up"
      },
      {
        "trend": "toto 株価",
        "search_volume": 20000,
        "start_date": "~16",
        "analysis": "trending_up"
      },
      {
        "trend": "サバ缶宇宙へ行くキャスト",
        "search_volume": 20000,
        "start_date": "~17",
        "analysis": "trending_up"
      },
      {
        "trend": "黒崎煌代",
        "search_volume": 20000,
        "start_date": "~10",
        "analysis": "timelapse"
      },
      {
        "trend": "オーディション",
        "search_volume": 10000,
        "start_date": "~7",
        "analysis": "trending_up"
      },
      {
        "trend": "木下グループ",
        "search_volume": 10000,
        "start_date": "~17",
        "analysis": "trending_up"
      },
      {
        "trend": "井原良太郎",
        "search_volume": 10000,
        "start_date": "~9",
        "analysis": "trending_up"
      },
      {
        "trend": "ロボ子さん",
        "search_volume": 10000,
        "start_date": "~11",
        "analysis": "trending_up"
      },
      {
        "trend": "和田まあや",
        "search_volume": 10000,
        "start_date": "~13",
        "analysis": "trending_up"
      },
      {
        "trend": "鍵山優真",
        "search_volume": 10000,
        "start_date": "~9",
        "analysis": "trending_up"
      },
      {
        "trend": "永野芽郁",
        "search_volume": 10000,
        "start_date": "~16",
        "analysis": "trending_up"
      },
      {
        "trend": "森田 崇",
        "search_volume": 10000,
        "start_date": "~11",
        "analysis": "trending_up"
      },
      {
        "trend": "カジュアル",
        "search_volume": 10000,
        "start_date": "~23",
        "analysis": "trending_up"
      }
    ],
    "GB": [
      {
        "trend": "man united vs leeds",
        "search_volume": 500000,
        "start_date": "~3",
        "analysis": "trending_up"
      },
      {
        "trend": "weather tomorrow",
        "search_volume": 100000,
        "start_date": "",
        "analysis": "timelapse"
      },
      {
        "trend": "monty don",
        "search_volume": 50000,
        "start_date": "~10",
        "analysis": "trending_up"
      },
      {
        "trend": "trump jesus",
        "search_volume": 50000,
        "start_date": "~13",
        "analysis": "trending_up"
      },
      {
        "trend": "erica stoll",
        "search_volume": 50000,
        "start_date": "~23",
        "analysis": "trending_up"
      },
      {
        "trend": "man united",
        "search_volume": 20000,
        "start_date": "~5",
        "analysis": "trending_up"
      },
      {
        "trend": "west brom points deduction",
        "search_volume": 20000,
        "start_date": "~11",
        "analysis": "trending_up"
      },
      {
        "trend": "smyths toys asbestos recall",
        "search_volume": 20000,
        "start_date": "~14",
        "analysis": "trending_up"
      },
      {
        "trend": "premier league",
        "search_volume": 20000,
        "start_date": "",
        "analysis": "trending_up"
      },
      {
        "trend": "praful hinge",
        "search_volume": 20000,
        "start_date": "~6",
        "analysis": "trending_up"
      },
      {
        "trend": "david haye girlfriend",
        "search_volume": 10000,
        "start_date": "",
        "analysis": "trending_up"
      },
      {
        "trend": "scottie scheffler masters complaint",
        "search_volume": 10000,
        "start_date": "~12",
        "analysis": "trending_up"
      },
      {
        "trend": "dominic frimpong",
        "search_volume": 10000,
        "start_date": "~11",
        "analysis": "trending_up"
      },
      {
        "trend": "srh vs rr",
        "search_volume": 10000,
        "start_date": "~7",
        "analysis": "trending_up"
      },
      {
        "trend": "montana",
        "search_volume": 10000,
        "start_date": "~21",
        "analysis": "trending_up"
      },
      {
        "trend": "ruby rose",
        "search_volume": 10000,
        "start_date": "~13",
        "analysis": "trending_up"
      },
      {
        "trend": "luke littler",
        "search_volume": 10000,
        "start_date": "~11",
        "analysis": "trending_up"
      },
      {
        "trend": "lasso",
        "search_volume": 10000,
        "start_date": "~21",
        "analysis": "trending_up"
      },
      {
        "trend": "outlook lite retirement may",
        "search_volume": 2510000,
        "start_date": "~14",
        "analysis": "trending_up"
      },
      {
        "trend": "axel rudakubana",
        "search_volume": 10000,
        "start_date": "~9",
        "analysis": "trending_up"
      },
      {
        "trend": "el nino uk summer impact",
        "search_volume": 10000,
        "start_date": "~11",
        "analysis": "trending_up"
      },
      {
        "trend": "european union",
        "search_volume": 10000,
        "start_date": "~7",
        "analysis": "trending_up"
      },
      {
        "trend": "sydney sweeney",
        "search_volume": 10000,
        "start_date": "~15",
        "analysis": "trending_up"
      },
      {
        "trend": "portugal",
        "search_volume": 10000,
        "start_date": "~12",
        "analysis": "timelapse"
      },
      {
        "trend": "gb news",
        "search_volume": 10000,
        "start_date": "~13",
        "analysis": "timelapse"
      }
    ],
    "DE": [
      {
        "trend": "steuer",
        "search_volume": 200000,
        "start_date": "~13",
        "analysis": "trending_up"
      },
      {
        "trend": "saharastaub",
        "search_volume": 100000,
        "start_date": "~13",
        "analysis": "trending_up"
      },
      {
        "trend": "trump attackiert papst",
        "search_volume": 50000,
        "start_date": "~11",
        "analysis": "trending_up"
      },
      {
        "trend": "grönemeyer",
        "search_volume": 50000,
        "start_date": "~2",
        "analysis": "trending_up"
      },
      {
        "trend": "lohnfortzahlung politik",
        "search_volume": 50000,
        "start_date": "~15",
        "analysis": "trending_up"
      },
      {
        "trend": "house of sweets",
        "search_volume": 50000,
        "start_date": "~22",
        "analysis": "timelapse"
      },
      {
        "trend": "max verstappen",
        "search_volume": 20000,
        "start_date": "~7",
        "analysis": "trending_up"
      },
      {
        "trend": "toastbrot",
        "search_volume": 20000,
        "start_date": "~16",
        "analysis": "trending_up"
      },
      {
        "trend": "daniel aminati",
        "search_volume": 20000,
        "start_date": "~8",
        "analysis": "trending_up"
      },
      {
        "trend": "dominic frimpong",
        "search_volume": 20000,
        "start_date": "~9",
        "analysis": "trending_up"
      },
      {
        "trend": "fußball-weltmeisterschaft",
        "search_volume": 20000,
        "start_date": "~10",
        "analysis": "trending_up"
      },
      {
        "trend": "sozialreform",
        "search_volume": 20000,
        "start_date": "~7",
        "analysis": "trending_up"
      },
      {
        "trend": "die ärzte tour",
        "search_volume": 202720000,
        "start_date": "~12",
        "analysis": "trending_up"
      },
      {
        "trend": "die toten vom bodensee",
        "search_volume": 20000,
        "start_date": "~4",
        "analysis": "trending_up"
      },
      {
        "trend": "lindt schokolade rewe",
        "search_volume": 20000,
        "start_date": "~2",
        "analysis": "trending_up"
      },
      {
        "trend": "sun matters",
        "search_volume": 20000,
        "start_date": "~16",
        "analysis": "trending_up"
      },
      {
        "trend": "sudan",
        "search_volume": 20000,
        "start_date": "~9",
        "analysis": "trending_up"
      },
      {
        "trend": "xiaomi",
        "search_volume": 20000,
        "start_date": "~9",
        "analysis": "trending_up"
      },
      {
        "trend": "buckelwal",
        "search_volume": 20000,
        "start_date": "~7",
        "analysis": "trending_up"
      },
      {
        "trend": "sandra flunger",
        "search_volume": 20000,
        "start_date": "~11",
        "analysis": "trending_up"
      },
      {
        "trend": "esther schweins let's dance",
        "search_volume": 20000,
        "start_date": "~2",
        "analysis": "trending_up"
      },
      {
        "trend": "jobcenter",
        "search_volume": 20000,
        "start_date": "~10",
        "analysis": "timelapse"
      },
      {
        "trend": "prinz harry",
        "search_volume": 20000,
        "start_date": "~10",
        "analysis": "timelapse"
      },
      {
        "trend": "tankstelle",
        "search_volume": 20000,
        "start_date": "~5",
        "analysis": "timelapse"
      },
      {
        "trend": "manunited – leeds",
        "search_volume": 10000,
        "start_date": "~2",
        "analysis": "trending_up"
      }
    ],
    "FR": [
      {
        "trend": "jean todt",
        "search_volume": 50000,
        "start_date": "~14",
        "analysis": "trending_up"
      },
      {
        "trend": "la dépêche",
        "search_volume": 50000,
        "start_date": "~9",
        "analysis": "trending_up"
      },
      {
        "trend": "trump pape",
        "search_volume": 50000,
        "start_date": "~14",
        "analysis": "trending_up"
      },
      {
        "trend": "maison",
        "search_volume": 50000,
        "start_date": "~11",
        "analysis": "timelapse"
      },
      {
        "trend": "évelyne dhéliat",
        "search_volume": 50000,
        "start_date": "~2",
        "analysis": "timelapse"
      },
      {
        "trend": "manchester united – leeds united",
        "search_volume": 20000,
        "start_date": "~2",
        "analysis": "trending_up"
      },
      {
        "trend": "destitution",
        "search_volume": 20000,
        "start_date": "~10",
        "analysis": "trending_up"
      },
      {
        "trend": "faustine bollaert",
        "search_volume": 20000,
        "start_date": "~10",
        "analysis": "trending_up"
      },
      {
        "trend": "espagne",
        "search_volume": 20000,
        "start_date": "~17",
        "analysis": "trending_up"
      },
      {
        "trend": "attentat algerie",
        "search_volume": 20000,
        "start_date": "~6",
        "analysis": "trending_up"
      },
      {
        "trend": "métro",
        "search_volume": 1220000,
        "start_date": "~11",
        "analysis": "trending_up"
      },
      {
        "trend": "retraite",
        "search_volume": 20000,
        "start_date": "~7",
        "analysis": "timelapse"
      },
      {
        "trend": "rodez – troyes",
        "search_volume": 10000,
        "start_date": "~2",
        "analysis": "trending_up"
      },
      {
        "trend": "eric cantona",
        "search_volume": 10000,
        "start_date": "~2",
        "analysis": "trending_up"
      },
      {
        "trend": "boeing kc-",
        "search_volume": 135,
        "start_date": "~7",
        "analysis": "trending_up"
      },
      {
        "trend": "lauren sánchez",
        "search_volume": 10000,
        "start_date": "~8",
        "analysis": "trending_up"
      },
      {
        "trend": "estelle laurier",
        "search_volume": 10000,
        "start_date": "~1",
        "analysis": "trending_up"
      },
      {
        "trend": "maladie",
        "search_volume": 10000,
        "start_date": "~5",
        "analysis": "trending_up"
      },
      {
        "trend": "monsieur le maire",
        "search_volume": 10000,
        "start_date": "~3",
        "analysis": "trending_up"
      },
      {
        "trend": "lafarge",
        "search_volume": 10000,
        "start_date": "~10",
        "analysis": "trending_up"
      },
      {
        "trend": "damian penaud",
        "search_volume": 10000,
        "start_date": "~10",
        "analysis": "trending_up"
      },
      {
        "trend": "sfr",
        "search_volume": 10000,
        "start_date": "~5",
        "analysis": "trending_up"
      },
      {
        "trend": "cyprien",
        "search_volume": 10000,
        "start_date": "~4",
        "analysis": "trending_up"
      },
      {
        "trend": "ministre de l’action et des comptes publics de france",
        "search_volume": 10000,
        "start_date": "~11",
        "analysis": "trending_up"
      },
      {
        "trend": "basic-fit",
        "search_volume": 10000,
        "start_date": "~11",
        "analysis": "trending_up"
      }
    ],
    "IN": [
      {
        "trend": "praful hinge",
        "search_volume": 2000000,
        "start_date": "~7",
        "analysis": "trending_up"
      },
      {
        "trend": "cbse result date april",
        "search_volume": 2026200000,
        "start_date": "~13",
        "analysis": "trending_up"
      },
      {
        "trend": "donovan ferreira",
        "search_volume": 200000,
        "start_date": "~2",
        "analysis": "timelapse"
      },
      {
        "trend": "srh बनाम rr",
        "search_volume": 100000,
        "start_date": "~7",
        "analysis": "trending_up"
      },
      {
        "trend": "nta neet",
        "search_volume": 100000,
        "start_date": "~22",
        "analysis": "trending_up"
      },
      {
        "trend": "मानसून",
        "search_volume": 100000,
        "start_date": "~7",
        "analysis": "timelapse"
      },
      {
        "trend": "man united vs leeds",
        "search_volume": 50000,
        "start_date": "~2",
        "analysis": "trending_up"
      },
      {
        "trend": "साँप",
        "search_volume": 50000,
        "start_date": "~13",
        "analysis": "trending_up"
      },
      {
        "trend": "noida news",
        "search_volume": 50000,
        "start_date": "~16",
        "analysis": "trending_up"
      },
      {
        "trend": "peshawar zalmi vs multan sultans",
        "search_volume": 50000,
        "start_date": "~7",
        "analysis": "trending_up"
      },
      {
        "trend": "noida",
        "search_volume": 50000,
        "start_date": "~16",
        "analysis": "trending_up"
      },
      {
        "trend": "rr srh",
        "search_volume": 50000,
        "start_date": "~7",
        "analysis": "trending_up"
      },
      {
        "trend": "abhishek sharma",
        "search_volume": 50000,
        "start_date": "~2",
        "analysis": "timelapse"
      },
      {
        "trend": "manchester united",
        "search_volume": 20000,
        "start_date": "~3",
        "analysis": "trending_up"
      },
      {
        "trend": "चलचित्र",
        "search_volume": 20000,
        "start_date": "~12",
        "analysis": "trending_up"
      },
      {
        "trend": "asia flights cancelled delayed",
        "search_volume": 20000,
        "start_date": "~18",
        "analysis": "trending_up"
      },
      {
        "trend": "tcs nashik news",
        "search_volume": 20000,
        "start_date": "~23",
        "analysis": "trending_up"
      },
      {
        "trend": "पाकिस्तान स्टॉक एक्सचेंज",
        "search_volume": 20000,
        "start_date": "~9",
        "analysis": "trending_up"
      },
      {
        "trend": "बिहार के मुख्यमंत्री",
        "search_volume": 20000,
        "start_date": "~5",
        "analysis": "trending_up"
      },
      {
        "trend": "ravindra jadeja",
        "search_volume": 20000,
        "start_date": "~2",
        "analysis": "timelapse"
      },
      {
        "trend": "రోహిత్ శర్మ",
        "search_volume": 20000,
        "start_date": "~12",
        "analysis": "timelapse"
      },
      {
        "trend": "தேர்தல்",
        "search_volume": 20000,
        "start_date": "~9",
        "analysis": "timelapse"
      },
      {
        "trend": "ആലപ്പി അഷ്റഫ്",
        "search_volume": 20000,
        "start_date": "~13",
        "analysis": "timelapse"
      },
      {
        "trend": "sandeep sharma",
        "search_volume": 20000,
        "start_date": "~1",
        "analysis": "timelapse"
      }
    ],
    "BR": [
      {
        "trend": "palmeiras",
        "search_volume": 500000,
        "start_date": "~2",
        "analysis": "timelapse"
      },
      {
        "trend": "flamengo",
        "search_volume": 500000,
        "start_date": "~2",
        "analysis": "timelapse"
      },
      {
        "trend": "manchester united x leeds",
        "search_volume": 100000,
        "start_date": "~3",
        "analysis": "trending_up"
      },
      {
        "trend": "enem",
        "search_volume": 100000,
        "start_date": "~17",
        "analysis": "trending_up"
      },
      {
        "trend": "cruzeiro",
        "search_volume": 100000,
        "start_date": "~2",
        "analysis": "timelapse"
      },
      {
        "trend": "palmeiras x",
        "search_volume": 100000,
        "start_date": "~2",
        "analysis": "timelapse"
      },
      {
        "trend": "al-hilal x al-sadd",
        "search_volume": 50000,
        "start_date": "~3",
        "analysis": "trending_up"
      },
      {
        "trend": "alexandre ramagem",
        "search_volume": 50000,
        "start_date": "~4",
        "analysis": "trending_up"
      },
      {
        "trend": "dolar",
        "search_volume": 50000,
        "start_date": "~3",
        "analysis": "trending_up"
      },
      {
        "trend": "paula toller",
        "search_volume": 50000,
        "start_date": "~23",
        "analysis": "trending_up"
      },
      {
        "trend": "crb x athletic",
        "search_volume": 50000,
        "start_date": "~22",
        "analysis": "trending_up"
      },
      {
        "trend": "décimo terceiro salário",
        "search_volume": 50000,
        "start_date": "~17",
        "analysis": "timelapse"
      },
      {
        "trend": "odair hellmann",
        "search_volume": 50000,
        "start_date": "~3",
        "analysis": "trending_up"
      },
      {
        "trend": "google",
        "search_volume": 50000,
        "start_date": "~4",
        "analysis": "timelapse"
      },
      {
        "trend": "dia",
        "search_volume": 20000,
        "start_date": "~7",
        "analysis": "trending_up"
      },
      {
        "trend": "marcos mion",
        "search_volume": 20000,
        "start_date": "~7",
        "analysis": "trending_up"
      },
      {
        "trend": "quilos mortais",
        "search_volume": 20000,
        "start_date": "~23",
        "analysis": "trending_up"
      },
      {
        "trend": "sandy",
        "search_volume": 20000,
        "start_date": "~23",
        "analysis": "trending_up"
      },
      {
        "trend": "kaio jorge",
        "search_volume": 20000,
        "start_date": "~5",
        "analysis": "trending_up"
      },
      {
        "trend": "trump papa",
        "search_volume": 20000,
        "start_date": "~10",
        "analysis": "trending_up"
      },
      {
        "trend": "concurso público",
        "search_volume": 20000,
        "start_date": "~24",
        "analysis": "trending_up"
      },
      {
        "trend": "atlético-go x londrina",
        "search_volume": 20000,
        "start_date": "~15",
        "analysis": "timelapse"
      },
      {
        "trend": "jogo do cruzeiro",
        "search_volume": 20000,
        "start_date": "~2",
        "analysis": "timelapse"
      },
      {
        "trend": "jeff bezos",
        "search_volume": 10000,
        "start_date": "~9",
        "analysis": "trending_up"
      },
      {
        "trend": "milton nascimento",
        "search_volume": 10000,
        "start_date": "~4",
        "analysis": "trending_up"
      }
    ],
    "CA": [
      {
        "trend": "nba playoffs",
        "search_volume": 50000,
        "start_date": "~21",
        "analysis": "trending_up"
      },
      {
        "trend": "canadiens – islanders",
        "search_volume": 50000,
        "start_date": "~18",
        "analysis": "timelapse"
      },
      {
        "trend": "man united vs leeds",
        "search_volume": 20000,
        "start_date": "~2",
        "analysis": "trending_up"
      },
      {
        "trend": "srh vs rr",
        "search_volume": 20000,
        "start_date": "~7",
        "analysis": "trending_up"
      },
      {
        "trend": "trump as jesus",
        "search_volume": 20000,
        "start_date": "~9",
        "analysis": "trending_up"
      },
      {
        "trend": "cibc",
        "search_volume": 20000,
        "start_date": "~6",
        "analysis": "timelapse"
      },
      {
        "trend": "masters golf tournament prize money",
        "search_volume": 20000,
        "start_date": "~6",
        "analysis": "trending_up"
      },
      {
        "trend": "nets vs raptors",
        "search_volume": 20000,
        "start_date": "~16",
        "analysis": "timelapse"
      },
      {
        "trend": "epic",
        "search_volume": 20000,
        "start_date": "~4",
        "analysis": "timelapse"
      },
      {
        "trend": "ruby rose",
        "search_volume": 10000,
        "start_date": "~14",
        "analysis": "trending_up"
      },
      {
        "trend": "mortgage loan",
        "search_volume": 10000,
        "start_date": "~21",
        "analysis": "trending_up"
      },
      {
        "trend": "outlook lite retirement may",
        "search_volume": 2510000,
        "start_date": "~10",
        "analysis": "trending_up"
      },
      {
        "trend": "euphoria season",
        "search_volume": 3,
        "start_date": "~20",
        "analysis": "trending_up"
      },
      {
        "trend": "google",
        "search_volume": 10000,
        "start_date": "~4",
        "analysis": "timelapse"
      },
      {
        "trend": "magic vs celtics",
        "search_volume": 10000,
        "start_date": "~5",
        "analysis": "timelapse"
      },
      {
        "trend": "lenyn sosa",
        "search_volume": 5000,
        "start_date": "~3",
        "analysis": "trending_up"
      },
      {
        "trend": "south korea",
        "search_volume": 5000,
        "start_date": "~9",
        "analysis": "trending_up"
      },
      {
        "trend": "britney spears",
        "search_volume": 5000,
        "start_date": "~21",
        "analysis": "trending_up"
      },
      {
        "trend": "montana",
        "search_volume": 5000,
        "start_date": "~16",
        "analysis": "trending_up"
      },
      {
        "trend": "jacob elordi",
        "search_volume": 5000,
        "start_date": "~22",
        "analysis": "trending_up"
      },
      {
        "trend": "séquestre",
        "search_volume": 5000,
        "start_date": "~7",
        "analysis": "trending_up"
      },
      {
        "trend": "canada byelections",
        "search_volume": 5000,
        "start_date": "~1",
        "analysis": "trending_up"
      },
      {
        "trend": "lane hutson",
        "search_volume": 5000,
        "start_date": "~21",
        "analysis": "trending_up"
      },
      {
        "trend": "hungary election viktor orban",
        "search_volume": 5000,
        "start_date": "~13",
        "analysis": "timelapse"
      },
      {
        "trend": "iran war hormuz",
        "search_volume": 5000,
        "start_date": "~5",
        "analysis": "timelapse"
      }
    ],
    "AU": [
      {
        "trend": "world quantum day",
        "search_volume": 20000,
        "start_date": "~6",
        "analysis": "trending_up"
      },
      {
        "trend": "masters",
        "search_volume": 20000,
        "start_date": "~3",
        "analysis": "timelapse"
      },
      {
        "trend": "man united vs leeds",
        "search_volume": 10000,
        "start_date": "~2",
        "analysis": "trending_up"
      },
      {
        "trend": "srh vs rr",
        "search_volume": 10000,
        "start_date": "~7",
        "analysis": "trending_up"
      },
      {
        "trend": "flight cancellation and delay",
        "search_volume": 10000,
        "start_date": "~16",
        "analysis": "trending_up"
      },
      {
        "trend": "who won australian idol",
        "search_volume": 202610000,
        "start_date": "~10",
        "analysis": "trending_up"
      },
      {
        "trend": "vanessa amorosi",
        "search_volume": 10000,
        "start_date": "~10",
        "analysis": "trending_up"
      },
      {
        "trend": "susan coyle",
        "search_volume": 10000,
        "start_date": "~19",
        "analysis": "trending_up"
      },
      {
        "trend": "zak butters umpire report language",
        "search_volume": 10000,
        "start_date": "~22",
        "analysis": "trending_up"
      },
      {
        "trend": "danny isaac descon-adcon tax debt",
        "search_volume": 5000,
        "start_date": "~16",
        "analysis": "trending_up"
      },
      {
        "trend": "pamela anderson",
        "search_volume": 5000,
        "start_date": "~14",
        "analysis": "trending_up"
      },
      {
        "trend": "mcdonald's australia",
        "search_volume": 5000,
        "start_date": "~16",
        "analysis": "trending_up"
      },
      {
        "trend": "market",
        "search_volume": 5000,
        "start_date": "~21",
        "analysis": "trending_up"
      },
      {
        "trend": "harry meghan australia visit",
        "search_volume": 5000,
        "start_date": "~21",
        "analysis": "trending_up"
      },
      {
        "trend": "child care",
        "search_volume": 5000,
        "start_date": "~24",
        "analysis": "trending_up"
      },
      {
        "trend": "trump jesus",
        "search_volume": 5000,
        "start_date": "~14",
        "analysis": "trending_up"
      },
      {
        "trend": "danny mafs",
        "search_volume": 5000,
        "start_date": "~9",
        "analysis": "trending_up"
      },
      {
        "trend": "security breach booking com",
        "search_volume": 5000,
        "start_date": "~9",
        "analysis": "timelapse"
      },
      {
        "trend": "hbo",
        "search_volume": 5000,
        "start_date": "~9",
        "analysis": "timelapse"
      },
      {
        "trend": "nba playoffs",
        "search_volume": 5000,
        "start_date": "~8",
        "analysis": "timelapse"
      },
      {
        "trend": "outlook lite retirement may",
        "search_volume": 252000,
        "start_date": "~14",
        "analysis": "trending_up"
      },
      {
        "trend": "king charles reportedly requests prince william leave camilla alone",
        "search_volume": 2000,
        "start_date": "~20",
        "analysis": "trending_up"
      },
      {
        "trend": "epl",
        "search_volume": 2000,
        "start_date": "",
        "analysis": "trending_up"
      },
      {
        "trend": "prince andrew house",
        "search_volume": 2000,
        "start_date": "~15",
        "analysis": "trending_up"
      },
      {
        "trend": "jacob elordi",
        "search_volume": 2000,
        "start_date": "~18",
        "analysis": "trending_up"
      }
    ],
    "IT": [
      {
        "trend": "fiorentina - lazio",
        "search_volume": 100000,
        "start_date": "~3",
        "analysis": "trending_up"
      },
      {
        "trend": "easyjet",
        "search_volume": 100000,
        "start_date": "~10",
        "analysis": "trending_up"
      },
      {
        "trend": "i cesaroni il ritorno",
        "search_volume": 50000,
        "start_date": "~3",
        "analysis": "trending_up"
      },
      {
        "trend": "trump papa leone",
        "search_volume": 50000,
        "start_date": "~14",
        "analysis": "trending_up"
      },
      {
        "trend": "easyjet linate",
        "search_volume": 20000,
        "start_date": "~6",
        "analysis": "trending_up"
      },
      {
        "trend": "busta paga",
        "search_volume": 20000,
        "start_date": "~8",
        "analysis": "trending_up"
      },
      {
        "trend": "gian piero gasperini",
        "search_volume": 20000,
        "start_date": "~9",
        "analysis": "trending_up"
      },
      {
        "trend": "ilaria salis",
        "search_volume": 20000,
        "start_date": "~5",
        "analysis": "timelapse"
      },
      {
        "trend": "manchester united - leeds",
        "search_volume": 10000,
        "start_date": "~2",
        "analysis": "trending_up"
      },
      {
        "trend": "pancreas",
        "search_volume": 10000,
        "start_date": "~3",
        "analysis": "trending_up"
      },
      {
        "trend": "la buona stella fiction",
        "search_volume": 10000,
        "start_date": "~4",
        "analysis": "trending_up"
      },
      {
        "trend": "matilda de angelis",
        "search_volume": 10000,
        "start_date": "~3",
        "analysis": "trending_up"
      },
      {
        "trend": "chiara balistreri",
        "search_volume": 10000,
        "start_date": "~7",
        "analysis": "trending_up"
      },
      {
        "trend": "novak djokovic",
        "search_volume": 10000,
        "start_date": "~8",
        "analysis": "trending_up"
      },
      {
        "trend": "antonio tajani",
        "search_volume": 10000,
        "start_date": "~4",
        "analysis": "trending_up"
      },
      {
        "trend": "stefano adamo",
        "search_volume": 10000,
        "start_date": "~7",
        "analysis": "trending_up"
      },
      {
        "trend": "euphoria",
        "search_volume": 3,
        "start_date": "~18",
        "analysis": "trending_up"
      },
      {
        "trend": "detrazione fiscale",
        "search_volume": 10000,
        "start_date": "~9",
        "analysis": "trending_up"
      },
      {
        "trend": "putin",
        "search_volume": 10000,
        "start_date": "~9",
        "analysis": "trending_up"
      },
      {
        "trend": "mare",
        "search_volume": 10000,
        "start_date": "~11",
        "analysis": "trending_up"
      },
      {
        "trend": "roma",
        "search_volume": 10000,
        "start_date": "~5",
        "analysis": "timelapse"
      },
      {
        "trend": "bolletta",
        "search_volume": 10000,
        "start_date": "~3",
        "analysis": "timelapse"
      },
      {
        "trend": "carlo monguzzi",
        "search_volume": 10000,
        "start_date": "~14",
        "analysis": "timelapse"
      },
      {
        "trend": "gas",
        "search_volume": 10000,
        "start_date": "~8",
        "analysis": "timelapse"
      },
      {
        "trend": "dragamine",
        "search_volume": 10000,
        "start_date": "~15",
        "analysis": "timelapse"
      }
    ],
    "ES": [
      {
        "trend": "levante - getafe",
        "search_volume": 50000,
        "start_date": "~2",
        "analysis": "trending_up"
      },
      {
        "trend": "sara carbonero",
        "search_volume": 50000,
        "start_date": "~21",
        "analysis": "trending_up"
      },
      {
        "trend": "tiempo",
        "search_volume": 50000,
        "start_date": "~15",
        "analysis": "timelapse"
      },
      {
        "trend": "telecinco en directo",
        "search_volume": 20000,
        "start_date": "~1",
        "analysis": "trending_up"
      },
      {
        "trend": "manchester united - leeds",
        "search_volume": 20000,
        "start_date": "~2",
        "analysis": "trending_up"
      },
      {
        "trend": "valladolid - eibar",
        "search_volume": 20000,
        "start_date": "~3",
        "analysis": "trending_up"
      },
      {
        "trend": "verano",
        "search_volume": 20000,
        "start_date": "~11",
        "analysis": "trending_up"
      },
      {
        "trend": "jorge rey",
        "search_volume": 20000,
        "start_date": "~7",
        "analysis": "trending_up"
      },
      {
        "trend": "juez peinado begoña gómez",
        "search_volume": 20000,
        "start_date": "~6",
        "analysis": "trending_up"
      },
      {
        "trend": "oscar freire",
        "search_volume": 10000,
        "start_date": "~9",
        "analysis": "trending_up"
      },
      {
        "trend": "conde de godo",
        "search_volume": 10000,
        "start_date": "~8",
        "analysis": "trending_up"
      },
      {
        "trend": "almendra",
        "search_volume": 5000,
        "start_date": "~3",
        "analysis": "trending_up"
      },
      {
        "trend": "cargador lidl",
        "search_volume": 5000,
        "start_date": "~6",
        "analysis": "trending_up"
      },
      {
        "trend": "telecinco directo",
        "search_volume": 5000,
        "start_date": "~1",
        "analysis": "trending_up"
      },
      {
        "trend": "límites de velocidad",
        "search_volume": 5000,
        "start_date": "~7",
        "analysis": "trending_up"
      },
      {
        "trend": "dia del beso",
        "search_volume": 5000,
        "start_date": "~14",
        "analysis": "trending_up"
      },
      {
        "trend": "fernando verdasco",
        "search_volume": 5000,
        "start_date": "~8",
        "analysis": "trending_up"
      },
      {
        "trend": "vacaciones",
        "search_volume": 5000,
        "start_date": "~23",
        "analysis": "trending_up"
      },
      {
        "trend": "tribunal constitucional",
        "search_volume": 5000,
        "start_date": "~15",
        "analysis": "trending_up"
      },
      {
        "trend": "onpe",
        "search_volume": 5000,
        "start_date": "~21",
        "analysis": "trending_up"
      },
      {
        "trend": "vox",
        "search_volume": 5000,
        "start_date": "~7",
        "analysis": "timelapse"
      },
      {
        "trend": "trump papa",
        "search_volume": 5000,
        "start_date": "~4",
        "analysis": "trending_up"
      },
      {
        "trend": "pirámide",
        "search_volume": 5000,
        "start_date": "~20",
        "analysis": "timelapse"
      },
      {
        "trend": "cameron norrie",
        "search_volume": 5000,
        "start_date": "~3",
        "analysis": "timelapse"
      },
      {
        "trend": "ibex",
        "search_volume": 355000,
        "start_date": "~1",
        "analysis": "timelapse"
      }
    ],
    "MX": [
      {
        "trend": "toluca - atl. san luis",
        "search_volume": 200000,
        "start_date": "~20",
        "analysis": "trending_up"
      },
      {
        "trend": "manchester united - leeds",
        "search_volume": 50000,
        "start_date": "~2",
        "analysis": "trending_up"
      },
      {
        "trend": "sep suspende clases mañana",
        "search_volume": 20000,
        "start_date": "~21",
        "analysis": "trending_up"
      },
      {
        "trend": "hoy no circula",
        "search_volume": 13,
        "start_date": "~16",
        "analysis": "trending_up"
      },
      {
        "trend": "festividad",
        "search_volume": 20000,
        "start_date": "~9",
        "analysis": "timelapse"
      },
      {
        "trend": "google",
        "search_volume": 20000,
        "start_date": "~7",
        "analysis": "timelapse"
      },
      {
        "trend": "al hilal - al-sadd",
        "search_volume": 10000,
        "start_date": "~3",
        "analysis": "trending_up"
      },
      {
        "trend": "alejandro zendejas",
        "search_volume": 10000,
        "start_date": "~17",
        "analysis": "trending_up"
      },
      {
        "trend": "tabla de goleo liga mx",
        "search_volume": 202610000,
        "start_date": "~10",
        "analysis": "trending_up"
      },
      {
        "trend": "angus cloud",
        "search_volume": 10000,
        "start_date": "~19",
        "analysis": "trending_up"
      },
      {
        "trend": "nba",
        "search_volume": 10000,
        "start_date": "~12",
        "analysis": "timelapse"
      },
      {
        "trend": "levante - getafe",
        "search_volume": 5000,
        "start_date": "~2",
        "analysis": "trending_up"
      },
      {
        "trend": "fiorentina - lazio",
        "search_volume": 5000,
        "start_date": "~2",
        "analysis": "trending_up"
      },
      {
        "trend": "clave única de registro de población",
        "search_volume": 5000,
        "start_date": "~21",
        "analysis": "trending_up"
      },
      {
        "trend": "club américa femenil",
        "search_volume": 5000,
        "start_date": "~19",
        "analysis": "trending_up"
      },
      {
        "trend": "bloqueo",
        "search_volume": 5000,
        "start_date": "~16",
        "analysis": "trending_up"
      },
      {
        "trend": "donde ver la mansion vip",
        "search_volume": 5000,
        "start_date": "~19",
        "analysis": "trending_up"
      },
      {
        "trend": "clima tijuana",
        "search_volume": 5000,
        "start_date": "~12",
        "analysis": "timelapse"
      },
      {
        "trend": "karol g",
        "search_volume": 5000,
        "start_date": "~11",
        "analysis": "timelapse"
      },
      {
        "trend": "el financiero",
        "search_volume": 5000,
        "start_date": "~4",
        "analysis": "timelapse"
      },
      {
        "trend": "lakers - jazz",
        "search_volume": 5000,
        "start_date": "~13",
        "analysis": "timelapse"
      },
      {
        "trend": "racing - river plate",
        "search_volume": 5000,
        "start_date": "~6",
        "analysis": "timelapse"
      },
      {
        "trend": "familia trump",
        "search_volume": 2000,
        "start_date": "~2",
        "analysis": "trending_up"
      },
      {
        "trend": "ruby rose",
        "search_volume": 2000,
        "start_date": "~5",
        "analysis": "trending_up"
      },
      {
        "trend": "dia del beso",
        "search_volume": 2000,
        "start_date": "~5",
        "analysis": "trending_up"
      }
    ]
  }
}